{
    "version": "2.28.15",
    "date": "2024-10-03",
    "entries": [
        {
            "type": "feature",
            "category": "AWS CodePipeline",
            "contributor": "",
            "description": "AWS CodePipeline introduces Commands action that enables you to easily run shell commands as part of your pipeline execution."
        },
        {
            "type": "feature",
            "category": "AWS Elemental MediaPackage v2",
            "contributor": "",
            "description": "Added support for ClipStartTime on the FilterConfiguration object on OriginEndpoint manifest settings objects. Added support for EXT-X-START tags on produced HLS child playlists."
        },
        {
            "type": "feature",
            "category": "AWS IoT",
            "contributor": "",
            "description": "This release adds support for Custom Authentication with X.509 Client Certificates, support for Custom Client Certificate validation, and support for selecting application protocol and authentication type without requiring TLS ALPN for customer's AWS IoT Domain Configurations."
        },
        {
            "type": "feature",
            "category": "AWS Marketplace Reporting Service",
            "contributor": "",
            "description": "The AWS Marketplace Reporting service introduces the GetBuyerDashboard API. This API returns a dashboard that provides visibility into your organization's AWS Marketplace agreements and associated spend across the AWS accounts in your organization."
        },
        {
            "type": "feature",
            "category": "Amazon Connect Service",
            "contributor": "",
            "description": "Public GetMetricDataV2 Grouping increase from 3 to 4"
        },
        {
            "type": "feature",
            "category": "Amazon Elastic Compute Cloud",
            "contributor": "",
            "description": "This release includes a new API for modifying instance cpu-options after launch."
        },
        {
            "type": "feature",
            "category": "Amazon QuickSight",
            "contributor": "",
            "description": "QuickSight: Add support for exporting and importing folders in AssetBundle APIs"
        },
        {
            "type": "feature",
            "category": "AWS SDK for Java v2",
            "contributor": "",
            "description": "Updated endpoint and partition metadata."
        }
    ]
}