{
    "version": "2.40.2",
    "date": "2025-12-04",
    "entries": [
        {
            "type": "bugfix",
            "category": "Apache 5 HTTP Client (Preview)",
            "contributor": "",
            "description": "Ignore negative values set `connectionTimeToLive`. There is no behavior change on the client as negative values have no meaning for Apache 5."
        },
        {
            "type": "feature",
            "category": "AWS Lambda",
            "contributor": "",
            "description": "Add DisallowedByVpcEncryptionControl to the LastUpdateStatusReasonCode and StateReasonCode enums to represent failures caused by VPC Encryption Controls."
        }
    ]
}